{
    "module_name": "quantum_keynav",
    "maintainer": "Marcus Ofenhed",
    "license": "MIT OR Apache-2.0",
    "features": {
        "digitizer": true,
        "deferred_exec": true
    },
    "keycodes": [
        {
            "key": "QK_KEYNAV_CUT_LEFT",
	    "alias": "KN_CTL"
        },
        {
            "key": "QK_KEYNAV_CUT_DOWN",
	    "alias": "KN_CTD"
        },
        {
            "key": "QK_KEYNAV_CUT_UP",
	    "alias": "KN_CTU"
        },
        {
            "key": "QK_KEYNAV_CUT_RIGHT",
	    "alias": "KN_CTR"
        },
        {
            "key": "QK_KEYNAV_MOVE_LEFT",
	    "alias": "KN_MVL"
        },
        {
            "key": "QK_KEYNAV_MOVE_DOWN",
	    "alias": "KN_MVD"
        },
        {
            "key": "QK_KEYNAV_MOVE_UP",
	    "alias": "KN_MVU"
        },
        {
            "key": "QK_KEYNAV_MOVE_RIGHT",
	    "alias": "KN_MVR"
        },
        {
            "key": "QK_KEYNAV_RESET"
        },
        {
            "key": "QK_KEYNAV_TOGGLE_ASSUMED_SCREEN_SIZE"
        },
        {
            "key": "QK_KEYNAV_BUTTON_1",
	    "alias": "KN_BTN1"
        },
        {
            "key": "QK_KEYNAV_BUTTON_2",
	    "alias": "KN_BTN2"
        },
        {
            "key": "QK_KEYNAV_DYNAMIC_MACRO_PLAY_1"
        },
        {
            "key": "QK_KEYNAV_DYNAMIC_MACRO_PLAY_2"
        }
    ]
}
